actxa_insights_test/__init__.py
actxa_insights_test/bgm.py
actxa_insights_test/clientsubs.py
actxa_insights_test/config.py
actxa_insights_test-0.0.6.dist-info/METADATA
actxa_insights_test-0.0.6.dist-info/WHEEL
actxa_insights_test-0.0.6.dist-info/top_level.txt
actxa_insights_test-0.0.6.dist-info/RECORD
