Metadata-Version: 2.4
Name: actxa_insights_test
Version: 0.0.6
Summary: SDK Python package for Actxa Insights
Author: Actxa Insights
Author-email: hadrian.gunawan@inphosoft.com
Requires-Python: >=3.9
Requires-Dist: requests
Dynamic: author
Dynamic: author-email
Dynamic: description
Dynamic: description-content-type
Dynamic: requires-dist
Dynamic: requires-python
Dynamic: summary
